Metadata-Version: 2.4
Name: hack4u_test02726
Version: 5.1.0
Summary: Una biblioteca para consultar cursos de hack4u
Home-page: https://hack4u.io
Author: Pablo Valero Martinez
Dynamic: author
Dynamic: description
Dynamic: description-content-type
Dynamic: home-page
Dynamic: summary
